sqlalchemy_omnisci/__init__.py
sqlalchemy_omnisci/_version.py
sqlalchemy_omnisci/base.py
sqlalchemy_omnisci/provision.py
sqlalchemy_omnisci/pyomnisci.py
sqlalchemy_omnisci/requirements.py
sqlalchemy_omnisci/util.py
sqlalchemy_omnisci/version.py
sqlalchemy_omnisci-0.1.3.dist-info/LICENSE
sqlalchemy_omnisci-0.1.3.dist-info/METADATA
sqlalchemy_omnisci-0.1.3.dist-info/WHEEL
sqlalchemy_omnisci-0.1.3.dist-info/entry_points.txt
sqlalchemy_omnisci-0.1.3.dist-info/top_level.txt
sqlalchemy_omnisci-0.1.3.dist-info/RECORD
